examples/demo.ipynb
examples/demo_vid/run_ani_swim01.mp4
examples/demo_vid/run_img_swim01.mp4
fish_simulator/VERSION
fish_simulator/__init__.py
fish_simulator/image_loader.py
fish_simulator/simulator.py
fish_simulator/transforms.py
fish_simulator/utils.py
fish_simulator/templates/template_img/head.png
fish_simulator/templates/template_img/segs/tail.png
fish_simulator/templates/template_img2/fish_head.png
fish_simulator/templates/template_img2/segs/00.png
fish_simulator/templates/template_img2/segs/01.png
fish_simulator/templates/template_img2/segs/02.png
fish_simulator/templates/template_img2/segs/03.png
fish_simulator/templates/template_img2/segs/04.png
fish_simulator/templates/template_img2/segs/05.png
fish_simulator/templates/template_img2/segs/06.png
fish_simulator/templates/template_img2/segs/07.png
fish_simulator/templates/template_img2/segs/08.png
fish_simulator/templates/template_img2/segs/09.png
fish_simulator/templates/template_img2/segs/10.png
fish_simulator/templates/template_img2/segs/11.png
fish_simulator/templates/template_img2/segs/12.png
fish_simulator/templates/template_img2/segs/13.png
fish_simulator/templates/template_img2/segs/14.png
fish_simulator/templates/template_img2/segs/15.png
fish_simulator/templates/template_img2/segs/16.png
fish_simulator/templates/template_img2/segs/17.png
fish_simulator/templates/template_img2/segs/18.png
fish_simulator/templates/template_img2/segs/19.png
fish_simulator/templates/template_img2/segs/20.png
fish_simulator/templates/template_img2/segs/21.png
fish_simulator/templates/template_img2/segs/22.png
fish_simulator/templates/template_img2/segs/23.png
fish_simulator/templates/template_img2/segs/24.png
fish_simulator/templates/template_img2/segs/25.png
fish_simulator/templates/template_img2/segs/26.png
fish_simulator/templates/template_img2/segs/27.png
fish_simulator/templates/template_img2/segs/28.png
fish_simulator/templates/template_img2/segs/29.png
fish_simulator/templates/template_img2/segs/30.png
fish_simulator-0.1.11.dist-info/LICENSE
fish_simulator-0.1.11.dist-info/METADATA
fish_simulator-0.1.11.dist-info/WHEEL
fish_simulator-0.1.11.dist-info/top_level.txt
fish_simulator-0.1.11.dist-info/RECORD
