Metadata-Version: 2.1
Name: fish_simulator
Version: 0.1.11
Summary: Simulate zebrafish swim from tail angle tracking data
Author-email: Thomas Soares Mullen <thomasmullen96@gmail.com>
License: MIT License
Project-URL: Homepage, https://github.com/ThomasMullen/fish_simulator
Project-URL: Bug Tracker, https://github.com/ThomasMullen/fish_simulator/issues
Classifier: Development Status :: 3 - Alpha
Classifier: Intended Audience :: Science/Research
Classifier: Intended Audience :: Education
Classifier: Topic :: Scientific/Engineering
Classifier: Topic :: Scientific/Engineering :: Artificial Intelligence
Classifier: Topic :: Scientific/Engineering :: Physics
Classifier: License :: OSI Approved :: MIT License
Classifier: Operating System :: OS Independent
Classifier: Programming Language :: Python :: 3
Classifier: Programming Language :: Python :: 3.9
Classifier: Programming Language :: Python :: 3.10
Classifier: Programming Language :: Python :: 3.11
Classifier: Programming Language :: Python :: 3 :: Only
Requires-Python: >=3.9
License-File: LICENSE
Requires-Dist: black
Requires-Dist: h5py
Requires-Dist: matplotlib
Requires-Dist: numpy
Requires-Dist: Pillow
Requires-Dist: scipy
Requires-Dist: twine
Requires-Dist: tqdm
Requires-Dist: wheel
Requires-Dist: cmcrameri
Requires-Dist: build
Requires-Dist: scikit-image
